nightlights/__init__.py
nightlights/download.py
nightlights/plotting.py
nightlights/process.py
nightlights/utils.py
nightlights-0.1.0.dist-info/LICENSE
nightlights-0.1.0.dist-info/METADATA
nightlights-0.1.0.dist-info/WHEEL
nightlights-0.1.0.dist-info/RECORD
