Metadata-Version: 2.3
Name: nightlights
Version: 0.1.0
Summary: This repository is to download and process of NASA's Black Marble Nightlights Suite.
License: MIT
Author: Jerónimo Luza
Author-email: jero.luza@gmail.com
Requires-Python: >=3.10,<4.0
Classifier: License :: OSI Approved :: MIT License
Classifier: Programming Language :: Python :: 3
Classifier: Programming Language :: Python :: 3.10
Classifier: Programming Language :: Python :: 3.11
Classifier: Programming Language :: Python :: 3.12
Classifier: Programming Language :: Python :: 3.13
Requires-Dist: cartopy (>=0.24.1,<0.25.0)
Requires-Dist: earthaccess (>=0.14.0,<0.15.0)
Requires-Dist: geopandas (>=1.0.1,<2.0.0)
Requires-Dist: h5py (>=3.13.0,<4.0.0)
Requires-Dist: imageio (>=2.37.0,<3.0.0)
Requires-Dist: matplotlib (>=3.10.1,<4.0.0)
Requires-Dist: osmnx (>=2.0.3,<3.0.0)
Requires-Dist: rasterio (>=1.4.3,<2.0.0)
Requires-Dist: rioxarray (>=0.19.0,<0.20.0)
Requires-Dist: seaborn (>=0.13.2,<0.14.0)
Requires-Dist: tabulate (>=0.9.0,<0.10.0)
Requires-Dist: xarray (>=2025.4.0,<2026.0.0)
